simplet2s/__init__.py
simplet2s/_native.py
simplet2s/_native__ffi.py
simplet2s/_native__lib.so
simplet2s-0.2.0.dist-info/LICENSE
simplet2s-0.2.0.dist-info/METADATA
simplet2s-0.2.0.dist-info/WHEEL
simplet2s-0.2.0.dist-info/top_level.txt
simplet2s-0.2.0.dist-info/RECORD
