Metadata-Version: 2.1
Name: simplet2s
Version: 0.2.0
Summary: A simple traditional Chinese to simplified Chinese converter
Home-page: https://github.com/bosondata/simplet2s-rs
Author: UNKNOWN
Author-email: UNKNOWN
License: UNKNOWN
Platform: any
Requires-Dist: milksnake
